ci/requirements/doc.yml
ci/requirements/environment.yml
doc/Makefile
doc/README.rst
doc/conf.py
doc/index.html
doc/index.rst
doc/sg_execution_times.rst
doc/_static/gedidb.css
doc/_static/images/GEDIDB_FLOWCHART.png
doc/_static/images/tileDB_fragment_structure.png
doc/_static/index-images/api_reference.svg
doc/_static/index-images/contributor.svg
doc/_static/index-images/getting_started.svg
doc/_static/index-images/user_guide.svg
doc/_static/logos/gediDB_logo.png
doc/_static/logos/gediDB_logo.svg
doc/_static/test_files/amazon.geojson
doc/_static/test_files/data_config.yml
doc/_static/test_files/test.geojson
doc/auto_examples/authentification.codeobj.json
doc/auto_examples/authentification.ipynb
doc/auto_examples/authentification.py
doc/auto_examples/authentification.rst
doc/auto_examples/authentification.zip
doc/auto_examples/auto_examples_jupyter.zip
doc/auto_examples/auto_examples_python.zip
doc/auto_examples/data_processor.codeobj.json
doc/auto_examples/data_processor.ipynb
doc/auto_examples/data_processor.py
doc/auto_examples/data_processor.rst
doc/auto_examples/data_processor.zip
doc/auto_examples/data_provider.codeobj.json
doc/auto_examples/data_provider.ipynb
doc/auto_examples/data_provider.py
doc/auto_examples/data_provider.rst
doc/auto_examples/data_provider.zip
doc/auto_examples/get_variable_list.codeobj.json
doc/auto_examples/get_variable_list.ipynb
doc/auto_examples/get_variable_list.py
doc/auto_examples/get_variable_list.rst
doc/auto_examples/get_variable_list.zip
doc/auto_examples/index.rst
doc/auto_examples/regional_tileDBdatabase.codeobj.json
doc/auto_examples/regional_tileDBdatabase.ipynb
doc/auto_examples/regional_tileDBdatabase.py
doc/auto_examples/regional_tileDBdatabase.rst
doc/auto_examples/regional_tileDBdatabase.zip
doc/auto_examples/sg_execution_times.rst
doc/auto_examples/images/thumb/sphx_glr_authentification_thumb.png
doc/auto_examples/images/thumb/sphx_glr_data_processor_thumb.png
gedidb-2025.9.24.dist-info/licenses/LICENSE
gedidb-2025.9.24.dist-info/METADATA
gedidb-2025.9.24.dist-info/WHEEL
gedidb-2025.9.24.dist-info/top_level.txt
gedidb-2025.9.24.dist-info/RECORD
