Metadata-Version: 2.4
Name: gedidb
Version: 2025.9.24
Summary: A toolbox to download, process, store and visualise Global Ecosystem Dynamics Investigation (GEDI) L2A-B and L4A-C data
Author-email: Simon Besnard <simon.besnard@gfz.de>, Felix Dombrowski <felix.dombrowski@uni-potsdam.de>, Amelia Holcomb <amelia.holcomb@gmail.com>
License:                       EUROPEAN UNION PUBLIC LICENCE v. 1.2
Project-URL: homepage, https://github.com/simonbesnard1/gedidb
Project-URL: documentation, https://gedidb.readthedocs.io/en/latest/
Project-URL: source, https://github.com/simonbesnard1/gedidb
Project-URL: tracker, https://github.com/simonbesnard1/gedidb/issues
Keywords: geospatial,GEDI,database
Classifier: Programming Language :: Python :: 3
Classifier: Programming Language :: Python :: 3.10
Classifier: Programming Language :: Python :: 3.11
Classifier: Programming Language :: Python :: 3.12
Classifier: Programming Language :: Python :: 3.13
Classifier: License :: OSI Approved :: European Union Public Licence 1.2 (EUPL 1.2)
Requires-Python: >=3.10
License-File: LICENSE
Requires-Dist: dask>=2025.9.1
Requires-Dist: distributed>=2025.9.1
Requires-Dist: geopandas>=1.1.1
Requires-Dist: h5py>=3.14.0
Requires-Dist: numpy>=2.3.3
Requires-Dist: pandas>=2.3.2
Requires-Dist: requests>=2.32.5
Requires-Dist: retry>=0.9.2
Requires-Dist: scipy>=1.16.2
Requires-Dist: tiledb>=0.34.2
Requires-Dist: xarray>=2025.9.0
Provides-Extra: accel
Requires-Dist: bottleneck>=1.3; extra == "accel"
Requires-Dist: numbagg>=0.8; extra == "accel"
Requires-Dist: flox>=0.8; extra == "accel"
Requires-Dist: opt_einsum>=3.3; extra == "accel"
Requires-Dist: numba>=0.58; extra == "accel"
Requires-Dist: cython>=3.0; extra == "accel"
Provides-Extra: io
Requires-Dist: boto3>=1.28; extra == "io"
Requires-Dist: s3fs>=2023.6; extra == "io"
Requires-Dist: fsspec>=2023.6; extra == "io"
Requires-Dist: zarr>=2.16; extra == "io"
Requires-Dist: netCDF4>=1.6; extra == "io"
Requires-Dist: h5netcdf>=1.2; extra == "io"
Requires-Dist: cftime>=1.6; extra == "io"
Requires-Dist: pooch>=1.7; extra == "io"
Requires-Dist: rasterio>=1.3; extra == "io"
Requires-Dist: pyproj>=3.6; extra == "io"
Requires-Dist: pydap; python_version < "3.10" and extra == "io"
Provides-Extra: viz
Requires-Dist: matplotlib>=3.7; extra == "viz"
Requires-Dist: seaborn>=0.13; extra == "viz"
Requires-Dist: cartopy>=0.22; extra == "viz"
Requires-Dist: nc-time-axis>=1.4; extra == "viz"
Requires-Dist: plotly>=5.17; extra == "viz"
Requires-Dist: holoviews>=1.17; extra == "viz"
Provides-Extra: debug
Requires-Dist: rich>=13.7; extra == "debug"
Requires-Dist: loguru>=0.7; extra == "debug"
Provides-Extra: full
Requires-Dist: bottleneck>=1.3; extra == "full"
Requires-Dist: numbagg>=0.8; extra == "full"
Requires-Dist: flox>=0.8; extra == "full"
Requires-Dist: opt_einsum>=3.3; extra == "full"
Requires-Dist: numba>=0.58; extra == "full"
Requires-Dist: cython>=3.0; extra == "full"
Requires-Dist: boto3>=1.28; extra == "full"
Requires-Dist: s3fs>=2023.6; extra == "full"
Requires-Dist: fsspec>=2023.6; extra == "full"
Requires-Dist: zarr>=2.16; extra == "full"
Requires-Dist: netCDF4>=1.6; extra == "full"
Requires-Dist: h5netcdf>=1.2; extra == "full"
Requires-Dist: cftime>=1.6; extra == "full"
Requires-Dist: pooch>=1.7; extra == "full"
Requires-Dist: rasterio>=1.3; extra == "full"
Requires-Dist: pyproj>=3.6; extra == "full"
Requires-Dist: pydap; python_version < "3.10" and extra == "full"
Requires-Dist: matplotlib>=3.7; extra == "full"
Requires-Dist: seaborn>=0.13; extra == "full"
Requires-Dist: cartopy>=0.22; extra == "full"
Requires-Dist: nc-time-axis>=1.4; extra == "full"
Requires-Dist: plotly>=5.17; extra == "full"
Requires-Dist: holoviews>=1.17; extra == "full"
Requires-Dist: rich>=13.7; extra == "full"
Requires-Dist: loguru>=0.7; extra == "full"
Provides-Extra: dev
Requires-Dist: pytest>=7.4; extra == "dev"
Requires-Dist: pytest-cov>=4.1; extra == "dev"
Requires-Dist: pytest-env>=1.0; extra == "dev"
Requires-Dist: pytest-xdist>=3.3; extra == "dev"
Requires-Dist: pytest-timeout>=2.2; extra == "dev"
Requires-Dist: hypothesis>=6.88; extra == "dev"
Requires-Dist: pre-commit>=3.5; extra == "dev"
Requires-Dist: ruff>=0.3; extra == "dev"
Requires-Dist: mypy>=1.7; extra == "dev"
Requires-Dist: black>=24.3; extra == "dev"
Requires-Dist: isort>=5.12; extra == "dev"
Dynamic: license-file
